{"lastUpdated":"2026-03-08T03:43:27.711Z","buyRegion":10000064,"sellRegion":10000022,"buyRegionName":"Essence","sellRegionName":"Stain","opportunities":[{"typeId":33195,"itemName":"Spatial Attunement Unit","buyPrice":1.01,"sellPrice":3500,"profitPerUnit":3498.99,"buyStation":"Algogille XIII - Federation Navy Testing Facilities","sellStation":"B-G1LG VI - Moon 3 - True Power Mining Outpost","roi":346434.65,"volumeAvailable":2,"maxProfit":6997.98},{"typeId":16118,"itemName":"CONCORD Officer Emblem","buyPrice":5300,"sellPrice":65000,"profitPerUnit":59700,"buyStation":"Algogille XIII - Federation Navy Testing Facilities","sellStation":"37S-KO VII - True Power Mining Outpost","roi":1126.42,"volumeAvailable":3,"maxProfit":179100},{"typeId":20,"itemName":"Kernite","buyPrice":450,"sellPrice":1500,"profitPerUnit":1050,"buyStation":"Atlangeins V - Moon 11 - Chemal Tech Factory","sellStation":"0G-A25 VI - Moon 20 - True Power Mining Outpost","roi":233.33,"volumeAvailable":613,"maxProfit":643650},{"typeId":20,"itemName":"Kernite","buyPrice":490,"sellPrice":1500,"profitPerUnit":1010,"buyStation":"Droselory VI - Moon 17 - CreoDron Warehouse","sellStation":"0G-A25 VI - Moon 20 - True Power Mining Outpost","roi":206.12,"volumeAvailable":613,"maxProfit":619130},{"typeId":20,"itemName":"Kernite","buyPrice":500,"sellPrice":1500,"profitPerUnit":1000,"buyStation":"Laurvier IX - Moon 2 - Modern Finances Depository","sellStation":"0G-A25 VI - Moon 20 - True Power Mining Outpost","roi":200,"volumeAvailable":613,"maxProfit":613000},{"typeId":20,"itemName":"Kernite","buyPrice":500,"sellPrice":1500,"profitPerUnit":1000,"buyStation":"Yona VI - Moon 5 - CreoDron Factory","sellStation":"0G-A25 VI - Moon 20 - True Power Mining Outpost","roi":200,"volumeAvailable":613,"maxProfit":613000},{"typeId":20,"itemName":"Kernite","buyPrice":569,"sellPrice":1500,"profitPerUnit":931,"buyStation":"Couster II - Moon 1 - Federal Navy Academy","sellStation":"0G-A25 VI - Moon 20 - True Power Mining Outpost","roi":163.62,"volumeAvailable":3,"maxProfit":2793},{"typeId":20,"itemName":"Kernite","buyPrice":579,"sellPrice":1500,"profitPerUnit":921,"buyStation":"Arnon X - Moon 8 - CBD Corporation Storage","sellStation":"0G-A25 VI - Moon 20 - True Power Mining Outpost","roi":159.07,"volumeAvailable":613,"maxProfit":564573},{"typeId":20,"itemName":"Kernite","buyPrice":590,"sellPrice":1500,"profitPerUnit":910,"buyStation":"Attyn V - Moon 13 - Poteque Pharmaceuticals Biotech Production","sellStation":"0G-A25 VI - Moon 20 - True Power Mining Outpost","roi":154.24,"volumeAvailable":613,"maxProfit":557830},{"typeId":20,"itemName":"Kernite","buyPrice":900,"sellPrice":1500,"profitPerUnit":600,"buyStation":"Mesybier II - TransStellar Shipping Storage","sellStation":"0G-A25 VI - Moon 20 - True Power Mining Outpost","roi":66.67,"volumeAvailable":613,"maxProfit":367800},{"typeId":20,"itemName":"Kernite","buyPrice":900,"sellPrice":1500,"profitPerUnit":600,"buyStation":"Deninard VIII - Moon 1 - The Scope Development Studio","sellStation":"0G-A25 VI - Moon 20 - True Power Mining Outpost","roi":66.67,"volumeAvailable":613,"maxProfit":367800},{"typeId":34,"itemName":"Tritanium","buyPrice":3.01,"sellPrice":4,"profitPerUnit":0.99,"buyStation":"Mies V - Moon 3 - Chemal Tech Warehouse","sellStation":"ZG8Q-N VII - Moon 6 - True Creations Testing Facilities","roi":32.89,"volumeAvailable":1565370,"maxProfit":1549716.3},{"typeId":20,"itemName":"Kernite","buyPrice":1188,"sellPrice":1500,"profitPerUnit":312,"buyStation":"Noghere VIII - Moon 1 - Core Complexion Inc. Factory","sellStation":"0G-A25 VI - Moon 20 - True Power Mining Outpost","roi":26.26,"volumeAvailable":613,"maxProfit":191256},{"typeId":20,"itemName":"Kernite","buyPrice":1189,"sellPrice":1500,"profitPerUnit":311,"buyStation":"Aporulie VII - Moon 16 - FedMart Retail Center","sellStation":"0G-A25 VI - Moon 20 - True Power Mining Outpost","roi":26.16,"volumeAvailable":613,"maxProfit":190643},{"typeId":20,"itemName":"Kernite","buyPrice":1199,"sellPrice":1500,"profitPerUnit":301,"buyStation":"Oursulaert VIII - Modern Finances Vault","sellStation":"0G-A25 VI - Moon 20 - True Power Mining Outpost","roi":25.1,"volumeAvailable":613,"maxProfit":184513},{"typeId":34,"itemName":"Tritanium","buyPrice":3.29,"sellPrice":4,"profitPerUnit":0.71,"buyStation":"Pemene VI - Moon 2 - Wiyrkomi Corporation Factory","sellStation":"ZG8Q-N VII - Moon 6 - True Creations Testing Facilities","roi":21.58,"volumeAvailable":414894,"maxProfit":294574.74},{"typeId":34,"itemName":"Tritanium","buyPrice":3.35,"sellPrice":4,"profitPerUnit":0.65,"buyStation":"Algogille IX - Moon 3 - Federal Administration Information Center","sellStation":"ZG8Q-N VII - Moon 6 - True Creations Testing Facilities","roi":19.4,"volumeAvailable":1250,"maxProfit":812.5},{"typeId":34,"itemName":"Tritanium","buyPrice":3.47,"sellPrice":4,"profitPerUnit":0.53,"buyStation":"Couster II - Moon 1 - Federal Navy Academy","sellStation":"ZG8Q-N VII - Moon 6 - True Creations Testing Facilities","roi":15.27,"volumeAvailable":1010048,"maxProfit":535325.44},{"typeId":34201,"itemName":"Accelerant Decryptor","buyPrice":165800,"sellPrice":190000,"profitPerUnit":24200,"buyStation":"Algogille XIII - Federation Navy Testing Facilities","sellStation":"4GQ-XQ IX - Moon 1 - True Creations Shipyard","roi":14.6,"volumeAvailable":1,"maxProfit":24200},{"typeId":15608,"itemName":"Imperial Navy Midshipman Insignia II","buyPrice":7000,"sellPrice":8000,"profitPerUnit":1000,"buyStation":"Algogille IX - Moon 3 - Federal Administration Information Center","sellStation":"T-8UOF VII - Moon 2 - True Power Logistic Support","roi":14.29,"volumeAvailable":3,"maxProfit":3000},{"typeId":15992,"itemName":"Imperial Navy Sergeant Insignia II","buyPrice":22000,"sellPrice":25000,"profitPerUnit":3000,"buyStation":"Algogille IX - Moon 3 - Federal Administration Information Center","sellStation":"37S-KO VII - True Power Mining Outpost","roi":13.64,"volumeAvailable":2,"maxProfit":6000},{"typeId":15992,"itemName":"Imperial Navy Sergeant Insignia II","buyPrice":22050,"sellPrice":25000,"profitPerUnit":2950,"buyStation":"Oursulaert VIII - Moon 2 - Astral Mining Inc. Mining Outpost","sellStation":"37S-KO VII - True Power Mining Outpost","roi":13.38,"volumeAvailable":1,"maxProfit":2950},{"typeId":15587,"itemName":"Federation Navy Midshipman Insignia I","buyPrice":3999,"sellPrice":4500,"profitPerUnit":501,"buyStation":"Mies V - Moon 3 - Federation Navy Assembly Plant","sellStation":"9O-ZTS II - Moon 1 - True Power Testing Facilities","roi":12.53,"volumeAvailable":4,"maxProfit":2004},{"typeId":30744,"itemName":"Neural Network Analyzer","buyPrice":180000,"sellPrice":200000,"profitPerUnit":20000,"buyStation":"Arnon IX - Moon 3 - Sisters of EVE Bureau","sellStation":"D9D-GD V - Moon 2 - True Creations Shipyard","roi":11.11,"volumeAvailable":1,"maxProfit":20000},{"typeId":15612,"itemName":"Imperial Navy Captain Insignia I","buyPrice":45510,"sellPrice":50000,"profitPerUnit":4490,"buyStation":"Oursulaert VIII - Moon 2 - Astral Mining Inc. Mining Outpost","sellStation":"0T-LIB V - Moon 5 - True Power Mining Outpost","roi":9.87,"volumeAvailable":3,"maxProfit":13470},{"typeId":15597,"itemName":"Caldari Navy Midshipman Insignia II","buyPrice":7400,"sellPrice":8000,"profitPerUnit":600,"buyStation":"Oursulaert VII - Moon 2 - Federal Intelligence Office Testing Facilities","sellStation":"T-8UOF VII - Moon 2 - True Power Logistic Support","roi":8.11,"volumeAvailable":9,"maxProfit":5400},{"typeId":15597,"itemName":"Caldari Navy Midshipman Insignia II","buyPrice":7430,"sellPrice":8000,"profitPerUnit":570,"buyStation":"Couster II - Moon 1 - Federal Navy Academy","sellStation":"T-8UOF VII - Moon 2 - True Power Logistic Support","roi":7.67,"volumeAvailable":1,"maxProfit":570},{"typeId":34,"itemName":"Tritanium","buyPrice":3.75,"sellPrice":4,"profitPerUnit":0.25,"buyStation":"Aporulie VIII - FedMart Retail Center","sellStation":"ZG8Q-N VII - Moon 6 - True Creations Testing Facilities","roi":6.67,"volumeAvailable":1704431,"maxProfit":426107.75},{"typeId":30744,"itemName":"Neural Network Analyzer","buyPrice":190000,"sellPrice":200000,"profitPerUnit":10000,"buyStation":"Mesokel I - Federal Navy Academy","sellStation":"D9D-GD V - Moon 2 - True Creations Shipyard","roi":5.26,"volumeAvailable":10,"maxProfit":100000},{"typeId":34,"itemName":"Tritanium","buyPrice":3.8,"sellPrice":4,"profitPerUnit":0.2,"buyStation":"Algogille XIII - Federation Navy Testing Facilities","sellStation":"ZG8Q-N VII - Moon 6 - True Creations Testing Facilities","roi":5.26,"volumeAvailable":1704431,"maxProfit":340886.2},{"typeId":34,"itemName":"Tritanium","buyPrice":3.8,"sellPrice":4,"profitPerUnit":0.2,"buyStation":"Duripant VII - Moon 6 - Federal Navy Academy","sellStation":"ZG8Q-N VII - Moon 6 - True Creations Testing Facilities","roi":5.26,"volumeAvailable":19903,"maxProfit":3980.6},{"typeId":30745,"itemName":"Sleeper Data Library","buyPrice":480000,"sellPrice":500000,"profitPerUnit":20000,"buyStation":"Mesokel I - Federal Navy Academy","sellStation":"Y-4U62 VIII - Moon 2 - True Creations Shipyard","roi":4.17,"volumeAvailable":4,"maxProfit":80000},{"typeId":15999,"itemName":"Caldari Navy Captain Insignia V","buyPrice":48010,"sellPrice":50000,"profitPerUnit":1990,"buyStation":"Oursulaert VIII - Moon 2 - Astral Mining Inc. Mining Outpost","sellStation":"9O-ZTS II - Moon 1 - True Power Testing Facilities","roi":4.14,"volumeAvailable":1,"maxProfit":1990},{"typeId":15598,"itemName":"Caldari Navy Midshipman Insignia III","buyPrice":14500,"sellPrice":15000,"profitPerUnit":500,"buyStation":"Oursulaert VII - Moon 2 - Federal Intelligence Office Testing Facilities","sellStation":"J-AYLV III - Moon 14 - True Power Mining Outpost","roi":3.45,"volumeAvailable":4,"maxProfit":2000},{"typeId":30745,"itemName":"Sleeper Data Library","buyPrice":490000,"sellPrice":500000,"profitPerUnit":10000,"buyStation":"Couster II - Moon 1 - Federal Navy Academy","sellStation":"Y-4U62 VIII - Moon 2 - True Creations Shipyard","roi":2.04,"volumeAvailable":1,"maxProfit":10000},{"typeId":30744,"itemName":"Neural Network Analyzer","buyPrice":198000,"sellPrice":200000,"profitPerUnit":2000,"buyStation":"Oursulaert III - Federation Navy Testing Facilities","sellStation":"D9D-GD V - Moon 2 - True Creations Shipyard","roi":1.01,"volumeAvailable":2,"maxProfit":4000},{"typeId":30746,"itemName":"Ancient Coordinates Database","buyPrice":1489000,"sellPrice":1500000,"profitPerUnit":11000,"buyStation":"Luminaire III (Astrin) - Moon 1 - Duvolle Laboratories Factory","sellStation":"6Y-0TW II - Moon 12 - True Creations Shipyard","roi":0.74,"volumeAvailable":2,"maxProfit":22000},{"typeId":30744,"itemName":"Neural Network Analyzer","buyPrice":199000,"sellPrice":200000,"profitPerUnit":1000,"buyStation":"Villore VII - Moon 8 - Quafe Company Factory","sellStation":"D9D-GD V - Moon 2 - True Creations Shipyard","roi":0.5,"volumeAvailable":24,"maxProfit":24000},{"typeId":30744,"itemName":"Neural Network Analyzer","buyPrice":199000,"sellPrice":200000,"profitPerUnit":1000,"buyStation":"Algogille XIII - Federation Navy Testing Facilities","sellStation":"D9D-GD V - Moon 2 - True Creations Shipyard","roi":0.5,"volumeAvailable":12,"maxProfit":12000},{"typeId":33577,"itemName":"Covert Research Tools","buyPrice":498000,"sellPrice":500000,"profitPerUnit":2000,"buyStation":"Oursulaert VII - Moon 1 - Federation Navy Testing Facilities","sellStation":"WEQT-K I - Moon 12 - True Power Mineral Reserve","roi":0.4,"volumeAvailable":2,"maxProfit":4000},{"typeId":30745,"itemName":"Sleeper Data Library","buyPrice":499000,"sellPrice":500000,"profitPerUnit":1000,"buyStation":"Algogille XIII - Federation Navy Testing Facilities","sellStation":"Y-4U62 VIII - Moon 2 - True Creations Shipyard","roi":0.2,"volumeAvailable":5,"maxProfit":5000},{"typeId":33577,"itemName":"Covert Research Tools","buyPrice":499000,"sellPrice":500000,"profitPerUnit":1000,"buyStation":"Oursulaert VII - Moon 2 - Federal Intelligence Office Testing Facilities","sellStation":"WEQT-K I - Moon 12 - True Power Mineral Reserve","roi":0.2,"volumeAvailable":12,"maxProfit":12000},{"typeId":30746,"itemName":"Ancient Coordinates Database","buyPrice":1499000,"sellPrice":1500000,"profitPerUnit":1000,"buyStation":"Algogille XIII - Federation Navy Testing Facilities","sellStation":"6Y-0TW II - Moon 12 - True Creations Shipyard","roi":0.07,"volumeAvailable":2,"maxProfit":2000},{"typeId":15588,"itemName":"Federation Navy Midshipman Insignia II","buyPrice":7999,"sellPrice":8000,"profitPerUnit":1,"buyStation":"Mies V - Moon 3 - Federation Navy Assembly Plant","sellStation":"J-AYLV III - Moon 14 - True Power Mining Outpost","roi":0.01,"volumeAvailable":2,"maxProfit":2}]}