{"lastUpdated":"2026-03-02T08:36:20.637Z","buyRegion":10000015,"sellRegion":10000057,"buyRegionName":"Venal","sellRegionName":"Outer Ring","opportunities":[{"typeId":34,"itemName":"Tritanium","buyPrice":2.41,"sellPrice":5,"profitPerUnit":2.59,"buyStation":"P-VYVL VII - Moon 1 - Guristas Assembly Plant","sellStation":"D5IW-F VIII - Moon 2 - Chemal Tech Factory","roi":107.47,"volumeAvailable":100000,"maxProfit":259000},{"typeId":2525,"itemName":"Oceanic Command Center","buyPrice":800000,"sellPrice":1220000,"profitPerUnit":420000,"buyStation":"PF-QHK VII - Moon 6 - Guristas Logistic Support","sellStation":"4C-B7X VII - Moon 12 - Chemal Tech Factory","roi":52.5,"volumeAvailable":1,"maxProfit":420000},{"typeId":9826,"itemName":"Carbon","buyPrice":350.1,"sellPrice":385.88,"profitPerUnit":35.78,"buyStation":"6NJ8-V VII - Moon 2 - Guristas Logistic Support","sellStation":"D5IW-F VIII - Moon 2 - Chemal Tech Factory","roi":10.22,"volumeAvailable":28,"maxProfit":1001.84}]}