{"lastUpdated":"2026-05-05T20:39:05.715Z","buyRegion":10000032,"sellRegion":10000058,"buyRegionName":"Sinq Laison","sellRegionName":"Fountain","opportunities":[{"typeId":15588,"itemName":"Federation Navy Midshipman Insignia II","buyPrice":101.1,"sellPrice":8000,"profitPerUnit":7898.9,"buyStation":"Dodixie IX - Moon 20 - Federation Navy Assembly Plant","sellStation":"Serpentis Prime VIII - Moon 2 - Serpentis Corporation Chemical Refinery","roi":7812.96,"volumeAvailable":2,"maxProfit":15797.8},{"typeId":24490,"itemName":"Mjolnir Rage Heavy Assault Missile","buyPrice":111.9,"sellPrice":800,"profitPerUnit":688.1,"buyStation":"Dodixie IX - Moon 20 - Federation Navy Assembly Plant","sellStation":"WY-9LL IX - Moon 1 - Serpentis Corporation Reprocessing Facility","roi":614.92,"volumeAvailable":20000,"maxProfit":13762000},{"typeId":24490,"itemName":"Mjolnir Rage Heavy Assault Missile","buyPrice":147,"sellPrice":800,"profitPerUnit":653,"buyStation":"Vittenyn VI - Moon 13 - Federation Navy Assembly Plant","sellStation":"WY-9LL IX - Moon 1 - Serpentis Corporation Reprocessing Facility","roi":444.22,"volumeAvailable":1488,"maxProfit":971664},{"typeId":1855,"itemName":"Ship Scanner II","buyPrice":1328000,"sellPrice":5000000,"profitPerUnit":3672000,"buyStation":"Dodixie IX - Moon 20 - Federation Navy Assembly Plant","sellStation":"WY-9LL IX - Moon 1 - Serpentis Corporation Reprocessing Facility","roi":276.51,"volumeAvailable":1,"maxProfit":3672000},{"typeId":15996,"itemName":"Caldari Navy Captain Insignia IV","buyPrice":9009,"sellPrice":30000,"profitPerUnit":20991,"buyStation":"Eglennaert I - Moon 6 - Astral Mining Inc. Mineral Reserve","sellStation":"Serpentis Prime II - Archangels Testing Facilities","roi":233,"volumeAvailable":4,"maxProfit":83964},{"typeId":32880,"itemName":"Venture","buyPrice":130000,"sellPrice":292700,"profitPerUnit":162700,"buyStation":"Vittenyn VI - Moon 13 - Federation Navy Assembly Plant","sellStation":"Serpentis Prime VI - Moon 1 - Serpentis Inquest Biotech Research Center","roi":125.15,"volumeAvailable":2,"maxProfit":325400},{"typeId":32880,"itemName":"Venture","buyPrice":150000,"sellPrice":292700,"profitPerUnit":142700,"buyStation":"Dodixie IX - Moon 20 - Federation Navy Assembly Plant","sellStation":"Serpentis Prime VI - Moon 1 - Serpentis Inquest Biotech Research Center","roi":95.13,"volumeAvailable":2,"maxProfit":285400},{"typeId":32880,"itemName":"Venture","buyPrice":150000,"sellPrice":292700,"profitPerUnit":142700,"buyStation":"Trosquesere V - Moon 10 - Duvolle Laboratories Factory","sellStation":"Serpentis Prime VI - Moon 1 - Serpentis Inquest Biotech Research Center","roi":95.13,"volumeAvailable":2,"maxProfit":285400},{"typeId":32880,"itemName":"Venture","buyPrice":150000,"sellPrice":292700,"profitPerUnit":142700,"buyStation":"Audaerne X - Moon 3 - Poteque Pharmaceuticals Biotech Production","sellStation":"Serpentis Prime VI - Moon 1 - Serpentis Inquest Biotech Research Center","roi":95.13,"volumeAvailable":2,"maxProfit":285400},{"typeId":3713,"itemName":"Vitoc","buyPrice":6500,"sellPrice":12071.4,"profitPerUnit":5571.4,"buyStation":"Dodixie IX - Moon 20 - Federation Navy Assembly Plant","sellStation":"Serpentis Prime II - Archangels Testing Facilities","roi":85.71,"volumeAvailable":50,"maxProfit":278570},{"typeId":3713,"itemName":"Vitoc","buyPrice":6750,"sellPrice":12071.4,"profitPerUnit":5321.4,"buyStation":"Vittenyn VI - Moon 13 - Federation Navy Assembly Plant","sellStation":"Serpentis Prime II - Archangels Testing Facilities","roi":78.84,"volumeAvailable":80,"maxProfit":425712},{"typeId":15626,"itemName":"Republic Fleet Midshipman Insignia II","buyPrice":4600,"sellPrice":8000,"profitPerUnit":3400,"buyStation":"Dodixie IX - Moon 20 - Federation Navy Assembly Plant","sellStation":"Serpentis Prime II - Archangels Testing Facilities","roi":73.91,"volumeAvailable":14,"maxProfit":47600},{"typeId":3713,"itemName":"Vitoc","buyPrice":7000,"sellPrice":12071.4,"profitPerUnit":5071.4,"buyStation":"Jel VIII - Moon 12 - Roden Shipyards Factory","sellStation":"Serpentis Prime II - Archangels Testing Facilities","roi":72.45,"volumeAvailable":40,"maxProfit":202856},{"typeId":15660,"itemName":"Republic Fleet Private Insignia III","buyPrice":17940,"sellPrice":30000,"profitPerUnit":12060,"buyStation":"Dodixie IX - Moon 20 - Federation Navy Assembly Plant","sellStation":"Serpentis Prime II - Archangels Testing Facilities","roi":67.22,"volumeAvailable":1,"maxProfit":12060},{"typeId":15608,"itemName":"Imperial Navy Midshipman Insignia II","buyPrice":5000,"sellPrice":8000,"profitPerUnit":3000,"buyStation":"Dodixie VIII - Moon 3 - Nugoeihuvi Corporation Development Studio","sellStation":"Serpentis Prime II - Archangels Testing Facilities","roi":60,"volumeAvailable":33,"maxProfit":99000},{"typeId":15591,"itemName":"Federation Navy Sergeant Major Insignia I","buyPrice":19160,"sellPrice":30000,"profitPerUnit":10840,"buyStation":"Dodixie IX - Moon 20 - Federation Navy Assembly Plant","sellStation":"Serpentis Prime II - Archangels Testing Facilities","roi":56.58,"volumeAvailable":2,"maxProfit":21680},{"typeId":32880,"itemName":"Venture","buyPrice":195000,"sellPrice":292700,"profitPerUnit":97700,"buyStation":"Eglennaert I - Moon 4 - Federation Navy Assembly Plant","sellStation":"Serpentis Prime VI - Moon 1 - Serpentis Inquest Biotech Research Center","roi":50.1,"volumeAvailable":2,"maxProfit":195400},{"typeId":32880,"itemName":"Venture","buyPrice":197000,"sellPrice":292700,"profitPerUnit":95700,"buyStation":"Trossere VII - Moon 3 - University of Caille","sellStation":"Serpentis Prime VI - Moon 1 - Serpentis Inquest Biotech Research Center","roi":48.58,"volumeAvailable":2,"maxProfit":191400},{"typeId":32880,"itemName":"Venture","buyPrice":198000,"sellPrice":292700,"profitPerUnit":94700,"buyStation":"Bourynes VII - Moon 2 - University of Caille","sellStation":"Serpentis Prime VI - Moon 1 - Serpentis Inquest Biotech Research Center","roi":47.83,"volumeAvailable":2,"maxProfit":189400},{"typeId":32880,"itemName":"Venture","buyPrice":200000,"sellPrice":292700,"profitPerUnit":92700,"buyStation":"Ney IV - University of Caille","sellStation":"Serpentis Prime VI - Moon 1 - Serpentis Inquest Biotech Research Center","roi":46.35,"volumeAvailable":2,"maxProfit":185400},{"typeId":32880,"itemName":"Venture","buyPrice":200000,"sellPrice":292700,"profitPerUnit":92700,"buyStation":"Croleur III - Moon 1 - Republic Security Services Testing Facilities","sellStation":"Serpentis Prime VI - Moon 1 - Serpentis Inquest Biotech Research Center","roi":46.35,"volumeAvailable":2,"maxProfit":185400},{"typeId":15612,"itemName":"Imperial Navy Captain Insignia I","buyPrice":35000,"sellPrice":50000,"profitPerUnit":15000,"buyStation":"Dodixie VIII - Moon 3 - Nugoeihuvi Corporation Development Studio","sellStation":"Serpentis Prime II - Archangels Testing Facilities","roi":42.86,"volumeAvailable":3,"maxProfit":45000},{"typeId":3713,"itemName":"Vitoc","buyPrice":8500,"sellPrice":12071.4,"profitPerUnit":3571.4,"buyStation":"Aufay I - Astral Mining Inc. Mining Outpost","sellStation":"Serpentis Prime II - Archangels Testing Facilities","roi":42.02,"volumeAvailable":80,"maxProfit":285712},{"typeId":32880,"itemName":"Venture","buyPrice":210000,"sellPrice":292700,"profitPerUnit":82700,"buyStation":"Parchanier VI - Core Complexion Inc. Warehouse","sellStation":"Serpentis Prime VI - Moon 1 - Serpentis Inquest Biotech Research Center","roi":39.38,"volumeAvailable":2,"maxProfit":165400},{"typeId":3713,"itemName":"Vitoc","buyPrice":9000,"sellPrice":12071.4,"profitPerUnit":3071.4,"buyStation":"Jel VIII - Moon 20 - Federation Navy Assembly Plant","sellStation":"Serpentis Prime II - Archangels Testing Facilities","roi":34.13,"volumeAvailable":20,"maxProfit":61428},{"typeId":15628,"itemName":"Republic Fleet Private Insignia I","buyPrice":15150,"sellPrice":20000,"profitPerUnit":4850,"buyStation":"Dodixie IX - Moon 20 - Federation Navy Assembly Plant","sellStation":"Serpentis Prime II - Archangels Testing Facilities","roi":32.01,"volumeAvailable":1,"maxProfit":4850},{"typeId":32880,"itemName":"Venture","buyPrice":225000,"sellPrice":292700,"profitPerUnit":67700,"buyStation":"Doussivitte VIII - Moon 8 - Chemal Tech Factory","sellStation":"Serpentis Prime VI - Moon 1 - Serpentis Inquest Biotech Research Center","roi":30.09,"volumeAvailable":2,"maxProfit":135400},{"typeId":16118,"itemName":"CONCORD Officer Emblem","buyPrice":50000,"sellPrice":65000,"profitPerUnit":15000,"buyStation":"Dodixie IX - Moon 20 - Federation Navy Assembly Plant","sellStation":"MN5N-X VIII - Moon 15 - Archangels Assembly Plant","roi":30,"volumeAvailable":2,"maxProfit":30000},{"typeId":32880,"itemName":"Venture","buyPrice":226500,"sellPrice":292700,"profitPerUnit":66200,"buyStation":"Gallareue I - Federal Freight Storage","sellStation":"Serpentis Prime VI - Moon 1 - Serpentis Inquest Biotech Research Center","roi":29.23,"volumeAvailable":2,"maxProfit":132400},{"typeId":60751,"itemName":"AEGIS Personnel File Backups","buyPrice":400000,"sellPrice":500000,"profitPerUnit":100000,"buyStation":"Dodixie IX - Moon 20 - Federation Navy Assembly Plant","sellStation":"MN5N-X VIII - Moon 15 - Archangels Assembly Plant","roi":25,"volumeAvailable":149,"maxProfit":14900000},{"typeId":3895,"itemName":"Security Connections","buyPrice":22990000,"sellPrice":28000000,"profitPerUnit":5010000,"buyStation":"Dodixie IX - Moon 20 - Federation Navy Assembly Plant","sellStation":"Serpentis Prime VI - Moon 1 - Serpentis Inquest Biotech Research Center","roi":21.79,"volumeAvailable":1,"maxProfit":5010000},{"typeId":3713,"itemName":"Vitoc","buyPrice":10000,"sellPrice":12071.4,"profitPerUnit":2071.4,"buyStation":"Jel VIII - Moon 1 - FedMart Warehouse","sellStation":"Serpentis Prime II - Archangels Testing Facilities","roi":20.71,"volumeAvailable":20,"maxProfit":41428},{"typeId":15598,"itemName":"Caldari Navy Midshipman Insignia III","buyPrice":12500,"sellPrice":15000,"profitPerUnit":2500,"buyStation":"Dodixie VIII - Moon 3 - Nugoeihuvi Corporation Development Studio","sellStation":"Serpentis Prime II - Archangels Testing Facilities","roi":20,"volumeAvailable":3,"maxProfit":7500},{"typeId":15609,"itemName":"Imperial Navy Midshipman Insignia III","buyPrice":12500,"sellPrice":15000,"profitPerUnit":2500,"buyStation":"Dodixie VIII - Moon 3 - Nugoeihuvi Corporation Development Studio","sellStation":"Serpentis Prime II - Archangels Testing Facilities","roi":20,"volumeAvailable":3,"maxProfit":7500},{"typeId":33577,"itemName":"Covert Research Tools","buyPrice":430000,"sellPrice":500000,"profitPerUnit":70000,"buyStation":"Augnais VI - Moon 1 - Poteque Pharmaceuticals Biotech Production","sellStation":"Serpentis Prime II - Archangels Testing Facilities","roi":16.28,"volumeAvailable":8,"maxProfit":560000},{"typeId":60752,"itemName":"AEGIS Fortification Schematics","buyPrice":880000,"sellPrice":1000000,"profitPerUnit":120000,"buyStation":"Dodixie IX - Moon 20 - Federation Navy Assembly Plant","sellStation":"Serpentis Prime VIII - Moon 2 - Serpentis Corporation Chemical Refinery","roi":13.64,"volumeAvailable":92,"maxProfit":11040000},{"typeId":15596,"itemName":"Caldari Navy Midshipman Insignia I","buyPrice":4000,"sellPrice":4500,"profitPerUnit":500,"buyStation":"Parchanier VI - Core Complexion Inc. Warehouse","sellStation":"Serpentis Prime VIII - Moon 2 - Serpentis Corporation Chemical Refinery","roi":12.5,"volumeAvailable":10,"maxProfit":5000},{"typeId":3721,"itemName":"Slaves","buyPrice":750.1,"sellPrice":834.75,"profitPerUnit":84.65,"buyStation":"Vylade VII - Moon 6 - Federation Navy Logistic Support","sellStation":"WY-9LL IX - Moon 1 - Serpentis Corporation Reprocessing Facility","roi":11.29,"volumeAvailable":13,"maxProfit":1100.45},{"typeId":3721,"itemName":"Slaves","buyPrice":750.1,"sellPrice":834.75,"profitPerUnit":84.65,"buyStation":"Vittenyn VI - Moon 13 - Federation Navy Assembly Plant","sellStation":"WY-9LL IX - Moon 1 - Serpentis Corporation Reprocessing Facility","roi":11.29,"volumeAvailable":20,"maxProfit":1693},{"typeId":33577,"itemName":"Covert Research Tools","buyPrice":449300,"sellPrice":500000,"profitPerUnit":50700,"buyStation":"Dodixie IX - Moon 20 - Federation Navy Assembly Plant","sellStation":"Serpentis Prime II - Archangels Testing Facilities","roi":11.28,"volumeAvailable":15,"maxProfit":760500},{"typeId":60753,"itemName":"AEGIS Covert Operations Reports","buyPrice":9000000,"sellPrice":10000000,"profitPerUnit":1000000,"buyStation":"Dodixie IX - Moon 20 - Federation Navy Assembly Plant","sellStation":"Serpentis Prime II - Archangels Testing Facilities","roi":11.11,"volumeAvailable":28,"maxProfit":28000000},{"typeId":15587,"itemName":"Federation Navy Midshipman Insignia I","buyPrice":4197,"sellPrice":4500,"profitPerUnit":303,"buyStation":"Dodixie IX - Moon 20 - Federation Navy Assembly Plant","sellStation":"Serpentis Prime II - Archangels Testing Facilities","roi":7.22,"volumeAvailable":2,"maxProfit":606},{"typeId":15607,"itemName":"Imperial Navy Midshipman Insignia I","buyPrice":4200,"sellPrice":4500,"profitPerUnit":300,"buyStation":"Parchanier IV - President Bureau","sellStation":"MN5N-X VII - Moon 5 - Archangels Assembly Plant","roi":7.14,"volumeAvailable":8,"maxProfit":2400},{"typeId":15611,"itemName":"Imperial Navy Sergeant Major Insignia I","buyPrice":28410,"sellPrice":30000,"profitPerUnit":1590,"buyStation":"Eglennaert I - Moon 6 - Astral Mining Inc. Mineral Reserve","sellStation":"Serpentis Prime II - Archangels Testing Facilities","roi":5.6,"volumeAvailable":4,"maxProfit":6360},{"typeId":33577,"itemName":"Covert Research Tools","buyPrice":475000,"sellPrice":500000,"profitPerUnit":25000,"buyStation":"Ney IV - University of Caille","sellStation":"Serpentis Prime II - Archangels Testing Facilities","roi":5.26,"volumeAvailable":7,"maxProfit":175000},{"typeId":30745,"itemName":"Sleeper Data Library","buyPrice":475200,"sellPrice":500000,"profitPerUnit":24800,"buyStation":"Dodixie IX - Moon 20 - Federation Navy Assembly Plant","sellStation":"WY-9LL VIII - Moon 3 - Dominations Testing Facilities","roi":5.22,"volumeAvailable":31,"maxProfit":768800},{"typeId":15611,"itemName":"Imperial Navy Sergeant Major Insignia I","buyPrice":28520,"sellPrice":30000,"profitPerUnit":1480,"buyStation":"Auvergne V - Moon 5 - Federal Intelligence Office Assembly Plant","sellStation":"Serpentis Prime II - Archangels Testing Facilities","roi":5.19,"volumeAvailable":1,"maxProfit":1480},{"typeId":30744,"itemName":"Neural Network Analyzer","buyPrice":193100,"sellPrice":200000,"profitPerUnit":6900,"buyStation":"Dodixie IX - Moon 20 - Federation Navy Assembly Plant","sellStation":"WY-9LL VIII - Moon 3 - Dominations Testing Facilities","roi":3.57,"volumeAvailable":18,"maxProfit":124200},{"typeId":15646,"itemName":"Federation Navy Command Sergeant Major Insignia I","buyPrice":48700,"sellPrice":50000,"profitPerUnit":1300,"buyStation":"Dodixie IX - Moon 20 - Federation Navy Assembly Plant","sellStation":"Serpentis Prime II - Archangels Testing Facilities","roi":2.67,"volumeAvailable":13,"maxProfit":16900},{"typeId":15612,"itemName":"Imperial Navy Captain Insignia I","buyPrice":48840,"sellPrice":50000,"profitPerUnit":1160,"buyStation":"Auvergne V - Moon 5 - Federal Intelligence Office Assembly Plant","sellStation":"Serpentis Prime II - Archangels Testing Facilities","roi":2.38,"volumeAvailable":1,"maxProfit":1160},{"typeId":15607,"itemName":"Imperial Navy Midshipman Insignia I","buyPrice":4400,"sellPrice":4500,"profitPerUnit":100,"buyStation":"Fricoure VIII - Moon 3 - Duvolle Laboratories Factory","sellStation":"MN5N-X VII - Moon 5 - Archangels Assembly Plant","roi":2.27,"volumeAvailable":10,"maxProfit":1000},{"typeId":15607,"itemName":"Imperial Navy Midshipman Insignia I","buyPrice":4438,"sellPrice":4500,"profitPerUnit":62,"buyStation":"Auvergne V - Moon 5 - Federal Intelligence Office Assembly Plant","sellStation":"MN5N-X VII - Moon 5 - Archangels Assembly Plant","roi":1.4,"volumeAvailable":1,"maxProfit":62},{"typeId":15611,"itemName":"Imperial Navy Sergeant Major Insignia I","buyPrice":29660,"sellPrice":30000,"profitPerUnit":340,"buyStation":"Brapelille IX - Moon 18 - Federal Administration Information Center","sellStation":"Serpentis Prime II - Archangels Testing Facilities","roi":1.15,"volumeAvailable":5,"maxProfit":1700},{"typeId":30746,"itemName":"Ancient Coordinates Database","buyPrice":1489000,"sellPrice":1500000,"profitPerUnit":11000,"buyStation":"Dodixie IX - Moon 20 - Federation Navy Assembly Plant","sellStation":"WY-9LL VIII - Moon 3 - Dominations Testing Facilities","roi":0.74,"volumeAvailable":7,"maxProfit":77000},{"typeId":15608,"itemName":"Imperial Navy Midshipman Insignia II","buyPrice":7999,"sellPrice":8000,"profitPerUnit":1,"buyStation":"Fricoure VIII - Moon 3 - Duvolle Laboratories Factory","sellStation":"Serpentis Prime II - Archangels Testing Facilities","roi":0.01,"volumeAvailable":11,"maxProfit":11}]}