{"lastUpdated":"2026-03-08T03:43:27.773Z","buyRegion":10000048,"sellRegion":10000012,"buyRegionName":"Placid","sellRegionName":"Curse","opportunities":[{"typeId":33195,"itemName":"Spatial Attunement Unit","buyPrice":1.01,"sellPrice":1500,"profitPerUnit":1498.99,"buyStation":"Stacmon VIII - Moon 6 - Material Acquisition Refinery","sellStation":"J7A-UR VI - Dominations Testing Facilities","roi":148414.85,"volumeAvailable":2,"maxProfit":2997.98},{"typeId":25592,"itemName":"Defective Current Pump","buyPrice":28.08,"sellPrice":602,"profitPerUnit":573.92,"buyStation":"Intaki V (Intaki Prime) - Moon 5 - Astral Mining Inc. Refinery","sellStation":"QFEW-K V - Moon 1 - Serpentis Corporation Chemical Refinery","roi":2043.87,"volumeAvailable":2,"maxProfit":1147.84},{"typeId":30013,"itemName":"Core Scanner Probe I","buyPrice":9887,"sellPrice":30900,"profitPerUnit":21013,"buyStation":"Aldranette IX - Moon 1 - FedMart Warehouse","sellStation":"J4UD-J VI - Moon 3 - Guardian Angels Testing Facilities","roi":212.53,"volumeAvailable":8,"maxProfit":168104},{"typeId":25599,"itemName":"Charred Micro Circuit","buyPrice":33.05,"sellPrice":100.5,"profitPerUnit":67.45,"buyStation":"Intaki V (Intaki Prime) - Moon 5 - Astral Mining Inc. Refinery","sellStation":"QFEW-K V - Moon 1 - Serpentis Corporation Chemical Refinery","roi":204.08,"volumeAvailable":3,"maxProfit":202.35},{"typeId":30013,"itemName":"Core Scanner Probe I","buyPrice":10460,"sellPrice":30900,"profitPerUnit":20440,"buyStation":"Osmeden IX - Moon 6 - University of Caille","sellStation":"J4UD-J VI - Moon 3 - Guardian Angels Testing Facilities","roi":195.41,"volumeAvailable":8,"maxProfit":163520},{"typeId":30013,"itemName":"Core Scanner Probe I","buyPrice":11300,"sellPrice":30900,"profitPerUnit":19600,"buyStation":"Stacmon V - Moon 9 - Federation Navy Assembly Plant","sellStation":"J4UD-J VI - Moon 3 - Guardian Angels Testing Facilities","roi":173.45,"volumeAvailable":8,"maxProfit":156800},{"typeId":25599,"itemName":"Charred Micro Circuit","buyPrice":36.83,"sellPrice":100.5,"profitPerUnit":63.67,"buyStation":"Stacmon VIII - Moon 6 - Material Acquisition Refinery","sellStation":"QFEW-K V - Moon 1 - Serpentis Corporation Chemical Refinery","roi":172.88,"volumeAvailable":32,"maxProfit":2037.44},{"typeId":30013,"itemName":"Core Scanner Probe I","buyPrice":14400,"sellPrice":30900,"profitPerUnit":16500,"buyStation":"Ostingele VIII - Moon 3 - FedMart Warehouse","sellStation":"J4UD-J VI - Moon 3 - Guardian Angels Testing Facilities","roi":114.58,"volumeAvailable":8,"maxProfit":132000},{"typeId":30013,"itemName":"Core Scanner Probe I","buyPrice":14970,"sellPrice":30900,"profitPerUnit":15930,"buyStation":"Stacmon VIII - Moon 6 - Material Acquisition Refinery","sellStation":"J4UD-J VI - Moon 3 - Guardian Angels Testing Facilities","roi":106.41,"volumeAvailable":8,"maxProfit":127440},{"typeId":30013,"itemName":"Core Scanner Probe I","buyPrice":14980,"sellPrice":30900,"profitPerUnit":15920,"buyStation":"Stacmon VII - Moon 1 - Impro Factory","sellStation":"J4UD-J VI - Moon 3 - Guardian Angels Testing Facilities","roi":106.28,"volumeAvailable":8,"maxProfit":127360},{"typeId":35657,"itemName":"100MN Y-S8 Compact Afterburner","buyPrice":196500,"sellPrice":400000,"profitPerUnit":203500,"buyStation":"Aldranette IX - Moon 1 - FedMart Warehouse","sellStation":"HLW-HP VI - Moon 7 - Guardian Angels Assembly Plant","roi":103.56,"volumeAvailable":21,"maxProfit":4273500},{"typeId":30013,"itemName":"Core Scanner Probe I","buyPrice":18990,"sellPrice":30900,"profitPerUnit":11910,"buyStation":"Ausmaert VII - Moon 5 - Ducia Foundry Refinery","sellStation":"J4UD-J VI - Moon 3 - Guardian Angels Testing Facilities","roi":62.72,"volumeAvailable":8,"maxProfit":95280},{"typeId":35657,"itemName":"100MN Y-S8 Compact Afterburner","buyPrice":248000,"sellPrice":400000,"profitPerUnit":152000,"buyStation":"Orvolle I - Federation Navy Assembly Plant","sellStation":"HLW-HP VI - Moon 7 - Guardian Angels Assembly Plant","roi":61.29,"volumeAvailable":50,"maxProfit":7600000},{"typeId":35,"itemName":"Pyerite","buyPrice":16.01,"sellPrice":25,"profitPerUnit":8.99,"buyStation":"Orvolle I - Federation Navy Assembly Plant","sellStation":"XX9-WV VII - Moon 3 - Salvation Angels Trading Post","roi":56.15,"volumeAvailable":17226,"maxProfit":154861.74},{"typeId":30013,"itemName":"Core Scanner Probe I","buyPrice":20000,"sellPrice":30900,"profitPerUnit":10900,"buyStation":"Vlillirier III - Moon 2 - Wiyrkomi Corporation Factory","sellStation":"J4UD-J VI - Moon 3 - Guardian Angels Testing Facilities","roi":54.5,"volumeAvailable":8,"maxProfit":87200},{"typeId":35657,"itemName":"100MN Y-S8 Compact Afterburner","buyPrice":265600,"sellPrice":400000,"profitPerUnit":134400,"buyStation":"Stacmon VII - Moon 1 - Impro Factory","sellStation":"HLW-HP VI - Moon 7 - Guardian Angels Assembly Plant","roi":50.6,"volumeAvailable":9,"maxProfit":1209600},{"typeId":25589,"itemName":"Malfunctioning Shield Emitter","buyPrice":140.1,"sellPrice":200.5,"profitPerUnit":60.4,"buyStation":"Stacmon VIII - Moon 6 - Material Acquisition Refinery","sellStation":"QFEW-K V - Moon 1 - Serpentis Corporation Chemical Refinery","roi":43.11,"volumeAvailable":33,"maxProfit":1993.2},{"typeId":35657,"itemName":"100MN Y-S8 Compact Afterburner","buyPrice":280000,"sellPrice":400000,"profitPerUnit":120000,"buyStation":"Stacmon V - Moon 9 - Federation Navy Assembly Plant","sellStation":"HLW-HP VI - Moon 7 - Guardian Angels Assembly Plant","roi":42.86,"volumeAvailable":2,"maxProfit":240000},{"typeId":34,"itemName":"Tritanium","buyPrice":3,"sellPrice":4.03,"profitPerUnit":1.03,"buyStation":"Mollin VI - Moon 5 - Material Acquisition Mining Outpost","sellStation":"CL-85V IX - Moon 2 - Archangels Assembly Plant","roi":34.33,"volumeAvailable":3,"maxProfit":3.09},{"typeId":17471,"itemName":"Veldspar III-Grade","buyPrice":7.55,"sellPrice":10.02,"profitPerUnit":2.47,"buyStation":"Slays VI - Moon 9 - Freedom Extension Storage","sellStation":"LJ-YSW IV - Moon 2 - Serpentis Corporation Reprocessing Facility","roi":32.72,"volumeAvailable":58,"maxProfit":143.26},{"typeId":34,"itemName":"Tritanium","buyPrice":3.1,"sellPrice":4.03,"profitPerUnit":0.93,"buyStation":"Stacmon VIII - Moon 6 - Material Acquisition Refinery","sellStation":"CL-85V IX - Moon 2 - Archangels Assembly Plant","roi":30,"volumeAvailable":11112,"maxProfit":10334.16},{"typeId":35657,"itemName":"100MN Y-S8 Compact Afterburner","buyPrice":308100,"sellPrice":400000,"profitPerUnit":91900,"buyStation":"Orvolle VI - Moon 1 - Federal Administration Bureau Offices","sellStation":"HLW-HP VI - Moon 7 - Guardian Angels Assembly Plant","roi":29.83,"volumeAvailable":5,"maxProfit":459500},{"typeId":30013,"itemName":"Core Scanner Probe I","buyPrice":24500,"sellPrice":30900,"profitPerUnit":6400,"buyStation":"Osmeden XII - Moon 1 - Federation Navy Assembly Plant","sellStation":"J4UD-J VI - Moon 3 - Guardian Angels Testing Facilities","roi":26.12,"volumeAvailable":8,"maxProfit":51200},{"typeId":34,"itemName":"Tritanium","buyPrice":3.2,"sellPrice":4.03,"profitPerUnit":0.83,"buyStation":"Brellystier IV - Moon 2 - Astral Mining Inc. Mineral Reserve","sellStation":"CL-85V IX - Moon 2 - Archangels Assembly Plant","roi":25.94,"volumeAvailable":9995446,"maxProfit":8296220.18},{"typeId":30745,"itemName":"Sleeper Data Library","buyPrice":399000,"sellPrice":500000,"profitPerUnit":101000,"buyStation":"Vlillirier VI - Moon 1 - Roden Shipyards Factory","sellStation":"Utopia VI - Moon 22 - Dominations Assembly Plant","roi":25.31,"volumeAvailable":3,"maxProfit":303000},{"typeId":17463,"itemName":"Scordite II-Grade","buyPrice":16,"sellPrice":20.01,"profitPerUnit":4.01,"buyStation":"Archavoinet II - Moon 17 - TransStellar Shipping Storage","sellStation":"LJ-YSW IV - Moon 2 - Serpentis Corporation Reprocessing Facility","roi":25.06,"volumeAvailable":122938,"maxProfit":492981.38},{"typeId":35,"itemName":"Pyerite","buyPrice":20,"sellPrice":25,"profitPerUnit":5,"buyStation":"Archavoinet II - Moon 17 - TransStellar Shipping Storage","sellStation":"XX9-WV VII - Moon 3 - Salvation Angels Trading Post","roi":25,"volumeAvailable":1664,"maxProfit":8320},{"typeId":30013,"itemName":"Core Scanner Probe I","buyPrice":25000,"sellPrice":30900,"profitPerUnit":5900,"buyStation":"Aubenall II - Paragon Fulfillment Center","sellStation":"J4UD-J VI - Moon 3 - Guardian Angels Testing Facilities","roi":23.6,"volumeAvailable":8,"maxProfit":47200},{"typeId":37,"itemName":"Isogen","buyPrice":175,"sellPrice":215,"profitPerUnit":40,"buyStation":"Osmeden XII - Moon 1 - Federation Navy Assembly Plant","sellStation":"YKE4-3 III - Moon 1 - Guardian Angels Testing Facilities","roi":22.86,"volumeAvailable":7071,"maxProfit":282840},{"typeId":35,"itemName":"Pyerite","buyPrice":21,"sellPrice":25,"profitPerUnit":4,"buyStation":"Brellystier IV - Moon 2 - Astral Mining Inc. Mineral Reserve","sellStation":"XX9-WV VII - Moon 3 - Salvation Angels Trading Post","roi":19.05,"volumeAvailable":3682350,"maxProfit":14729400},{"typeId":34,"itemName":"Tritanium","buyPrice":3.48,"sellPrice":4.03,"profitPerUnit":0.55,"buyStation":"Brarel V - Moon 3 - Federal Freight Storage","sellStation":"CL-85V IX - Moon 2 - Archangels Assembly Plant","roi":15.8,"volumeAvailable":6025341,"maxProfit":3313937.55},{"typeId":34,"itemName":"Tritanium","buyPrice":3.48,"sellPrice":4.03,"profitPerUnit":0.55,"buyStation":"Vivanier V - Moon 3 - Duvolle Laboratories Factory","sellStation":"CL-85V IX - Moon 2 - Archangels Assembly Plant","roi":15.8,"volumeAvailable":9253944,"maxProfit":5089669.2},{"typeId":36,"itemName":"Mexallon","buyPrice":48.01,"sellPrice":55.01,"profitPerUnit":7,"buyStation":"Orvolle I - Federation Navy Assembly Plant","sellStation":"CL-1JE V - Moon 1 - Serpentis Corporation Chemical Refinery","roi":14.58,"volumeAvailable":8104,"maxProfit":56728},{"typeId":35657,"itemName":"100MN Y-S8 Compact Afterburner","buyPrice":349900,"sellPrice":400000,"profitPerUnit":50100,"buyStation":"Intaki V (Intaki Prime) - Federation Navy Anchorage","sellStation":"HLW-HP VI - Moon 7 - Guardian Angels Assembly Plant","roi":14.32,"volumeAvailable":10,"maxProfit":501000},{"typeId":16240,"itemName":"Catalyst","buyPrice":700000,"sellPrice":800000,"profitPerUnit":100000,"buyStation":"Osmeden IX - Moon 6 - University of Caille","sellStation":"G-0Q86 VII - Moon 1 - Guardian Angels Assembly Plant","roi":14.29,"volumeAvailable":3,"maxProfit":300000},{"typeId":3721,"itemName":"Slaves","buyPrice":750.1,"sellPrice":834.75,"profitPerUnit":84.65,"buyStation":"Intaki V (Intaki Prime) - Moon 5 - Astral Mining Inc. Refinery","sellStation":"LJ-YSW IV - Moon 2 - Serpentis Corporation Reprocessing Facility","roi":11.29,"volumeAvailable":4,"maxProfit":338.6},{"typeId":45999,"itemName":"Agency 'Pyrolancea' DB5 Dose II","buyPrice":9000000,"sellPrice":10000000,"profitPerUnit":1000000,"buyStation":"Cumemare III - Moon 13 - Caldari Business Tribunal","sellStation":"UW9B-F X - Guardian Angels Logistic Support","roi":11.11,"volumeAvailable":3,"maxProfit":3000000},{"typeId":45999,"itemName":"Agency 'Pyrolancea' DB5 Dose II","buyPrice":9000000,"sellPrice":10000000,"profitPerUnit":1000000,"buyStation":"Gare V - Moon 10 - Ishukone Corporation Factory","sellStation":"UW9B-F X - Guardian Angels Logistic Support","roi":11.11,"volumeAvailable":2,"maxProfit":2000000},{"typeId":1230,"itemName":"Veldspar","buyPrice":10,"sellPrice":11,"profitPerUnit":1,"buyStation":"Intaki V (Intaki Prime) - Moon 5 - Astral Mining Inc. Refinery","sellStation":"G-0Q86 VII - Moon 1 - Guardian Angels Assembly Plant","roi":10,"volumeAvailable":48000,"maxProfit":48000},{"typeId":34,"itemName":"Tritanium","buyPrice":3.7,"sellPrice":4.03,"profitPerUnit":0.33,"buyStation":"Alparena V - Moon 4 - Federal Navy Academy","sellStation":"CL-85V IX - Moon 2 - Archangels Assembly Plant","roi":8.92,"volumeAvailable":9995446,"maxProfit":3298497.18},{"typeId":34,"itemName":"Tritanium","buyPrice":3.71,"sellPrice":4.03,"profitPerUnit":0.32,"buyStation":"Gare V - Moon 10 - Ishukone Corporation Factory","sellStation":"CL-85V IX - Moon 2 - Archangels Assembly Plant","roi":8.63,"volumeAvailable":355,"maxProfit":113.6},{"typeId":35,"itemName":"Pyerite","buyPrice":23.03,"sellPrice":25,"profitPerUnit":1.97,"buyStation":"Vestouve IX - Moon 11 - Aliastra Warehouse","sellStation":"XX9-WV VII - Moon 3 - Salvation Angels Trading Post","roi":8.55,"volumeAvailable":148,"maxProfit":291.56},{"typeId":3713,"itemName":"Vitoc","buyPrice":11200,"sellPrice":12066.83,"profitPerUnit":866.83,"buyStation":"Intaki V (Intaki Prime) - Federation Navy Anchorage","sellStation":"G-0Q86 V - Moon 5 - Archangels Logistic Support","roi":7.74,"volumeAvailable":40,"maxProfit":34673.2},{"typeId":3713,"itemName":"Vitoc","buyPrice":11210,"sellPrice":12066.83,"profitPerUnit":856.83,"buyStation":"Osmeden XII - Moon 1 - Federation Navy Assembly Plant","sellStation":"G-0Q86 V - Moon 5 - Archangels Logistic Support","roi":7.64,"volumeAvailable":34,"maxProfit":29132.22},{"typeId":3713,"itemName":"Vitoc","buyPrice":11210,"sellPrice":12066.83,"profitPerUnit":856.83,"buyStation":"Orvolle VI - Moon 1 - Federal Administration Bureau Offices","sellStation":"G-0Q86 V - Moon 5 - Archangels Logistic Support","roi":7.64,"volumeAvailable":20,"maxProfit":17136.6},{"typeId":3713,"itemName":"Vitoc","buyPrice":11210,"sellPrice":12066.83,"profitPerUnit":856.83,"buyStation":"Intaki V (Intaki Prime) - Moon 5 - Astral Mining Inc. Refinery","sellStation":"G-0Q86 V - Moon 5 - Archangels Logistic Support","roi":7.64,"volumeAvailable":40,"maxProfit":34273.2},{"typeId":37,"itemName":"Isogen","buyPrice":200,"sellPrice":215,"profitPerUnit":15,"buyStation":"Intaki V (Intaki Prime) - Moon 5 - Astral Mining Inc. Refinery","sellStation":"YKE4-3 III - Moon 1 - Guardian Angels Testing Facilities","roi":7.5,"volumeAvailable":18510,"maxProfit":277650},{"typeId":16275,"itemName":"Strontium Clathrates","buyPrice":3500,"sellPrice":3700,"profitPerUnit":200,"buyStation":"Cumemare III - Moon 13 - Caldari Business Tribunal","sellStation":"XX9-WV VII - Moon 3 - Salvation Angels Trading Post","roi":5.71,"volumeAvailable":500,"maxProfit":100000},{"typeId":30747,"itemName":"Sleeper Drone AI Nexus","buyPrice":4800000,"sellPrice":5000000,"profitPerUnit":200000,"buyStation":"Slays VII - Moon 3 - Center for Advanced Studies School","sellStation":"G-G78S XI - Moon 3 - Dominations Assembly Plant","roi":4.17,"volumeAvailable":3,"maxProfit":600000},{"typeId":34,"itemName":"Tritanium","buyPrice":3.89,"sellPrice":4.03,"profitPerUnit":0.14,"buyStation":"Intaki V (Intaki Prime) - Federation Navy Anchorage","sellStation":"CL-85V IX - Moon 2 - Archangels Assembly Plant","roi":3.6,"volumeAvailable":7532448,"maxProfit":1054542.72},{"typeId":37,"itemName":"Isogen","buyPrice":208,"sellPrice":215,"profitPerUnit":7,"buyStation":"Vestouve IX - Moon 11 - Aliastra Warehouse","sellStation":"YKE4-3 III - Moon 1 - Guardian Angels Testing Facilities","roi":3.37,"volumeAvailable":3670,"maxProfit":25690},{"typeId":34,"itemName":"Tritanium","buyPrice":3.9,"sellPrice":4.03,"profitPerUnit":0.13,"buyStation":"Stacmon VII - Moon 1 - Impro Factory","sellStation":"CL-85V IX - Moon 2 - Archangels Assembly Plant","roi":3.33,"volumeAvailable":122849,"maxProfit":15970.37},{"typeId":35,"itemName":"Pyerite","buyPrice":24.53,"sellPrice":25,"profitPerUnit":0.47,"buyStation":"Orvolle VI - Moon 1 - Federal Administration Bureau Offices","sellStation":"XX9-WV VII - Moon 3 - Salvation Angels Trading Post","roi":1.92,"volumeAvailable":3682350,"maxProfit":1730704.5},{"typeId":3713,"itemName":"Vitoc","buyPrice":11900,"sellPrice":12066.83,"profitPerUnit":166.83,"buyStation":"Maut VIII - Inner Zone Shipping Storage","sellStation":"G-0Q86 V - Moon 5 - Archangels Logistic Support","roi":1.4,"volumeAvailable":1555,"maxProfit":259420.65},{"typeId":25603,"itemName":"Melted Capacitor Console","buyPrice":2501,"sellPrice":2513,"profitPerUnit":12,"buyStation":"Intaki V (Intaki Prime) - Moon 5 - Astral Mining Inc. Refinery","sellStation":"QFEW-K V - Moon 1 - Serpentis Corporation Chemical Refinery","roi":0.48,"volumeAvailable":1,"maxProfit":12},{"typeId":45999,"itemName":"Agency 'Pyrolancea' DB5 Dose II","buyPrice":9990000,"sellPrice":10000000,"profitPerUnit":10000,"buyStation":"Vlillirier III - Moon 2 - Wiyrkomi Corporation Factory","sellStation":"UW9B-F X - Guardian Angels Logistic Support","roi":0.1,"volumeAvailable":3,"maxProfit":30000},{"typeId":62517,"itemName":"Compressed Veldspar II-Grade","buyPrice":10,"sellPrice":10.01,"profitPerUnit":0.01,"buyStation":"Stacmon V - Moon 9 - Federation Navy Assembly Plant","sellStation":"LJ-YSW IV - Moon 2 - Serpentis Corporation Reprocessing Facility","roi":0.1,"volumeAvailable":51,"maxProfit":0.51}]}