{"lastUpdated":"2026-03-02T08:36:20.305Z","buyRegion":10000030,"sellRegion":10000061,"buyRegionName":"Heimatar","sellRegionName":"Tenerifis","opportunities":[{"typeId":1153,"itemName":"Antimatter Charge L Blueprint","buyPrice":1000000,"sellPrice":5000000,"profitPerUnit":4000000,"buyStation":"Amamake VI - Moon 1 - Expert Distribution Warehouse","sellStation":"Station 1046664001931","roi":400,"volumeAvailable":1,"maxProfit":4000000},{"typeId":2525,"itemName":"Oceanic Command Center","buyPrice":81000,"sellPrice":200000,"profitPerUnit":119000,"buyStation":"Bundindus IV - Moon 7 - Imperial Armaments Factory","sellStation":"Station 1046664001931","roi":146.91,"volumeAvailable":38,"maxProfit":4522000},{"typeId":2393,"itemName":"Bacteria","buyPrice":380,"sellPrice":528,"profitPerUnit":148,"buyStation":"Larkugei IX - Republic Military School","sellStation":"Station 1046664001931","roi":38.95,"volumeAvailable":32240,"maxProfit":4771520},{"typeId":11688,"itemName":"Particle Accelerator Unit","buyPrice":25000,"sellPrice":30010,"profitPerUnit":5010,"buyStation":"Rens VI - Moon 8 - Brutor Tribe Treasury","sellStation":"Station 1046664001931","roi":20.04,"volumeAvailable":100,"maxProfit":501000},{"typeId":3645,"itemName":"Water","buyPrice":400,"sellPrice":462,"profitPerUnit":62,"buyStation":"Larkugei IX - Republic Military School","sellStation":"Station 1046664001931","roi":15.5,"volumeAvailable":22140,"maxProfit":1372680},{"typeId":16635,"itemName":"Evaporite Deposits","buyPrice":270.2,"sellPrice":310.6,"profitPerUnit":40.4,"buyStation":"Abudban VIII - Moon 6 - Six Kin Development Production Plant","sellStation":"Station 1046664001931","roi":14.95,"volumeAvailable":103,"maxProfit":4161.2},{"typeId":650,"itemName":"Nereus","buyPrice":2250000,"sellPrice":2540000,"profitPerUnit":290000,"buyStation":"Lustrevik VII - Moon 9 - Brutor Tribe Academy","sellStation":"Station 1046664001931","roi":12.89,"volumeAvailable":1,"maxProfit":290000},{"typeId":640,"itemName":"Scorpion","buyPrice":142000000,"sellPrice":159500000,"profitPerUnit":17500000,"buyStation":"Rens VI - Moon 8 - Brutor Tribe Treasury","sellStation":"Station 1046664001931","roi":12.32,"volumeAvailable":1,"maxProfit":17500000},{"typeId":47466,"itemName":"Praxis","buyPrice":240000000,"sellPrice":261400000,"profitPerUnit":21400000,"buyStation":"Loguttur I - Republic Military School","sellStation":"Station 1046664001931","roi":8.92,"volumeAvailable":1,"maxProfit":21400000},{"typeId":2398,"itemName":"Reactive Metals","buyPrice":375.1,"sellPrice":402.8,"profitPerUnit":27.7,"buyStation":"Rens VI - Moon 8 - Brutor Tribe Treasury","sellStation":"Station 1046664001931","roi":7.38,"volumeAvailable":16546,"maxProfit":458324.2},{"typeId":9848,"itemName":"Robotics","buyPrice":70530,"sellPrice":75010,"profitPerUnit":4480,"buyStation":"Rens VI - Moon 8 - Brutor Tribe Treasury","sellStation":"Station 1046664001931","roi":6.35,"volumeAvailable":730,"maxProfit":3270400},{"typeId":35,"itemName":"Pyerite","buyPrice":17,"sellPrice":17.81,"profitPerUnit":0.81,"buyStation":"Dammalin I - Quafe Company Factory","sellStation":"Station 1046664001931","roi":4.76,"volumeAvailable":75858,"maxProfit":61444.98},{"typeId":3828,"itemName":"Construction Blocks","buyPrice":8000,"sellPrice":8157,"profitPerUnit":157,"buyStation":"Gerek V - Moon 3 - Republic University","sellStation":"Station 1046664001931","roi":1.96,"volumeAvailable":2750,"maxProfit":431750}]}