{"lastUpdated":"2026-03-02T08:36:20.566Z","buyRegion":10000038,"sellRegion":10000009,"buyRegionName":"The Bleak Lands","sellRegionName":"Insmother","opportunities":[{"typeId":3645,"itemName":"Water","buyPrice":440,"sellPrice":536,"profitPerUnit":96,"buyStation":"Kuomi VI - Moon 2 - Ducia Foundry Refinery","sellStation":"Station 1049588174021","roi":21.82,"volumeAvailable":136100,"maxProfit":13065600},{"typeId":35660,"itemName":"50MN Quad LiF Restrained Microwarpdrive","buyPrice":24520,"sellPrice":27550,"profitPerUnit":3030,"buyStation":"Kamela V - 24th Imperial Crusade Logistic Support","sellStation":"Station 1049588174021","roi":12.36,"volumeAvailable":2,"maxProfit":6060},{"typeId":25605,"itemName":"Armor Plates","buyPrice":20010,"sellPrice":21420,"profitPerUnit":1410,"buyStation":"Sasiekko IV - Moon 2 - Amarr Constructions Warehouse","sellStation":"Station 1049588174021","roi":7.05,"volumeAvailable":5,"maxProfit":7050},{"typeId":11325,"itemName":"1600mm Rolled Tungsten Compact Plates","buyPrice":500000,"sellPrice":510900,"profitPerUnit":10900,"buyStation":"Lamaa IX - Moon 23 - Ducia Foundry Mineral Reserve","sellStation":"Station 1049588174021","roi":2.18,"volumeAvailable":19,"maxProfit":207100}]}